remote_resources/__init__.py
remote_resources/enums.py
remote_resources/models.py
remote_resources/querysets.py
remote_resources/db_property_cache/__init__.py
remote_resources/db_property_cache/querysets.py
remote_resources/management/__init__.py
remote_resources/management/download.py
remote_resources/management/mixins.py
remote_resources/utils/__init__.py
remote_resources/utils/itertools.py
remote_resources/utils/querysets.py
tests/__init__.py
django_remote_resources-0.3.0rc0.dist-info/LICENSE
django_remote_resources-0.3.0rc0.dist-info/METADATA
django_remote_resources-0.3.0rc0.dist-info/WHEEL
django_remote_resources-0.3.0rc0.dist-info/top_level.txt
django_remote_resources-0.3.0rc0.dist-info/RECORD
