Metadata-Version: 2.1
Name: django-remote-resources
Version: 0.3.0rc0
Summary: Sync remote API resources to Django models
Home-page: https://github.com/kaoslabsinc/django-remote-resources
Author: Kaos Labs Inc.
Author-email: keyvan@keyvanm.com
License: BSD-3-Clause
Keywords: django,api,resource,sync
Classifier: Environment :: Web Environment
Classifier: Framework :: Django
Classifier: Framework :: Django :: 3.2
Classifier: Intended Audience :: Developers
Classifier: License :: OSI Approved :: BSD License
Classifier: Operating System :: OS Independent
Classifier: Programming Language :: Python
Classifier: Programming Language :: Python :: 3
Classifier: Programming Language :: Python :: 3 :: Only
Classifier: Programming Language :: Python :: 3.7
Classifier: Programming Language :: Python :: 3.8
Classifier: Programming Language :: Python :: 3.9
Classifier: Topic :: Internet :: WWW/HTTP
Classifier: Topic :: Internet :: WWW/HTTP :: Dynamic Content
License-File: LICENSE
Requires-Dist: django (>=3.2)
Requires-Dist: django-building-blocks (>=0.1.0a7)
Provides-Extra: test
Requires-Dist: tox ; extra == 'test'
Requires-Dist: pytest-django ; extra == 'test'
Requires-Dist: pytest-pythonpath ; extra == 'test'
Requires-Dist: pytest-cov ; extra == 'test'
